{
  "saved_at": "2026-07-17T09:57:53.086635+00:00",
  "opportunity": {
    "招标单位": "青岛前湾集装箱码头有限责任公司",
    "招标单位行业分类": "交通物流",
    "项目名称": "山东港口青岛港QQCT轮胎吊2026年视频监控覆盖采购项目",
    "截止日期": "2026-07-23 08:30:00",
    "项目编号": "SPGBX-20260716006001-01",
    "采购内容": "采购硬盘录像机、硬盘、交换机、网线、UPS、显示器、大模型筒机、支架、收发器、跳线等视频监控设备",
    "源网址": "http://www.ygcgfw.com/gggs/001002/001002001/20260717/0c8373a7-716e-4131-b07f-769223ddea9b.html",
    "我司业务相关度": "低",
    "匹配产品": "无明确匹配产品",
    "匹配理由": "项目涉及视频监控覆盖，可能包含智能分析或智能问答功能，匹配企业级AI智能体产品。"
  }
}