{
  "saved_at": "2026-07-17T02:16:14.992431+00:00",
  "opportunity": {
    "招标单位": "巴马瑶族自治县人民医院",
    "项目名称": "巴马县域医共体乡镇卫生院“AI辅助+医疗”胸痛救治单元建设（重）",
    "截止日期": "2026-07-23 11:00:00",
    "项目编号": "HCZC2026-J1-270043-GXTZ",
    "采购内容": "巴马县域医共体乡镇卫生院“AI辅助+医疗”胸痛救治单元建设1项，包括心电一张网系统1套、数字式心电图机及配套设备35套、展示屏1台",
    "源网址": "https://www.ggzy.gov.cn/information/deal/html/b/450000/0201/20260716/004538648e7b59d94463a3bbf32f3ddc5c3e.html",
    "我司业务相关度": "低",
    "匹配产品": "无明确匹配产品",
    "匹配理由": "采购内容主要为医疗设备（心电图机等）和心电一张网系统，AI辅助仅作为概念性描述，无具体AI平台、智能体或财税需求，与VZOOM三类产品均不匹配"
  }
}